project_to_epub/__init__.py
project_to_epub/__main__.py
project_to_epub/cli.py
project_to_epub/converter.py
project_to_epub-0.1.4.dist-info/licenses/LICENSE
project_to_epub-0.1.4.dist-info/METADATA
project_to_epub-0.1.4.dist-info/WHEEL
project_to_epub-0.1.4.dist-info/entry_points.txt
project_to_epub-0.1.4.dist-info/top_level.txt
project_to_epub-0.1.4.dist-info/RECORD
