Metadata-Version: 2.4
Name: project-to-epub
Version: 0.1.4
Summary: Convert a software project directory into an EPUB file for offline code reading
Author: Project-to-EPUB Team
License: MIT
Project-URL: Repository, https://github.com/PsychArch/project-to-epub
Project-URL: Documentation, https://github.com/PsychArch/project-to-epub#readme
Classifier: Development Status :: 3 - Alpha
Classifier: Environment :: Console
Classifier: Intended Audience :: Developers
Classifier: License :: OSI Approved :: MIT License
Classifier: Programming Language :: Python :: 3
Classifier: Programming Language :: Python :: 3.8
Classifier: Programming Language :: Python :: 3.9
Classifier: Programming Language :: Python :: 3.10
Classifier: Programming Language :: Python :: 3.11
Classifier: Programming Language :: Python :: 3.12
Classifier: Programming Language :: Python :: 3.13
Classifier: Topic :: Software Development :: Documentation
Classifier: Topic :: Text Processing :: Markup :: HTML
Classifier: Topic :: Utilities
Requires-Python: >=3.8.1
License-File: LICENSE
Requires-Dist: typer>=0.9.0
Requires-Dist: pygments>=2.15.0
Requires-Dist: pathspec>=0.11.0
Requires-Dist: pyyaml>=6.0
Requires-Dist: markdown>=3.5.1
Provides-Extra: dev
Requires-Dist: pytest>=7.0.0; extra == "dev"
Requires-Dist: black>=23.0.0; extra == "dev"
Requires-Dist: isort>=5.12.0; extra == "dev"
Requires-Dist: flake8>=6.0.0; extra == "dev"
Requires-Dist: ruff>=0.2.0; extra == "dev"
Requires-Dist: ebooklib>=0.17.1; extra == "dev"
Dynamic: license-file
